genome_kmers/__init__.py
genome_kmers/kmers.py
genome_kmers/profiling.py
genome_kmers/sequence_collection.py
genome_kmers/simple_kmers.py
genome_kmers-1.0.0.dist-info/LICENSE
genome_kmers-1.0.0.dist-info/METADATA
genome_kmers-1.0.0.dist-info/WHEEL
genome_kmers-1.0.0.dist-info/RECORD
