Metadata-Version: 2.1
Name: genome-kmers
Version: 1.0.0
Summary: fast and memory-efficient genomic k-mer calculations
License: LICENSE
Author: Matthew Perkett
Requires-Python: >=3.9,<4.0
Classifier: Development Status :: 4 - Beta
Classifier: Intended Audience :: Science/Research
Classifier: License :: OSI Approved :: MIT License
Classifier: License :: Other/Proprietary License
Classifier: Programming Language :: Python :: 3
Classifier: Programming Language :: Python :: 3.9
Classifier: Programming Language :: Python :: 3.10
Classifier: Programming Language :: Python :: 3.11
Classifier: Programming Language :: Python :: 3.12
Requires-Dist: biopython (>=1.83,<2.0)
Requires-Dist: h5py (>=3.11.0,<4.0.0)
Requires-Dist: numba (>=0.59.1,<0.60.0)
Requires-Dist: numpy (>=1.26.4,<2.0.0)
Requires-Dist: pandas (>=2.2.2,<3.0.0)
